src/__init__.py
src/tarsafe.py
tarsafe/__init__.py
tarsafe/tarsafe.py
test/__init__.py
test/test_tarsafe.py
tarsafe-0.0.5.dist-info/LICENSE
tarsafe-0.0.5.dist-info/METADATA
tarsafe-0.0.5.dist-info/WHEEL
tarsafe-0.0.5.dist-info/top_level.txt
tarsafe-0.0.5.dist-info/RECORD
