Metadata-Version: 2.1
Name: tarsafe
Version: 0.0.5
Summary: A safe subclass of the TarFile class for interacting with tar files. Can be used as a direct drop-in replacement for safe usage of extractall()
Home-page: https://github.com/beatsbears/tarsafe
Author: Andrew Scott
License: MIT License
Platform: UNKNOWN
Requires-Python: >=3.6
